buffer_app.py
buffer_app-1.0.0.dist-info/METADATA
buffer_app-1.0.0.dist-info/WHEEL
buffer_app-1.0.0.dist-info/entry_points.txt
buffer_app-1.0.0.dist-info/top_level.txt
buffer_app-1.0.0.dist-info/RECORD
