Metadata-Version: 2.1
Name: buffer-app
Version: 1.0.0
Summary: A quick GUI to quickly calculate buffer dilution and adjustment.
Home-page: https://github.com/Paradoxdruid/pychemistry/tree/master/scripts/buffer_app
Author: Andrew J. Bonham
Author-email: abonham@msudenver.edu
License: GPLv3
Keywords: chemistry,buffer,biochemistry
Platform: UNKNOWN
Classifier: Programming Language :: Python :: 3
Classifier: Programming Language :: Python :: 3.6
Classifier: Programming Language :: Python :: 3.7
Classifier: Programming Language :: Python :: 3.8
Classifier: Programming Language :: Python :: 3.9
Classifier: Programming Language :: Python :: 3 :: Only
Classifier: License :: OSI Approved :: GNU General Public License v3 (GPLv3)
Classifier: Operating System :: OS Independent
Requires-Python: >=3.6
Requires-Dist: PySimpleGUI
